LenHTTP-2.2.1.dist-info/METADATA
LenHTTP-2.2.1.dist-info/WHEEL
LenHTTP-2.2.1.dist-info/top_level.txt
LenHTTP-2.2.1.dist-info/LICENSE
LenHTTP-2.2.1.dist-info/RECORD
lenhttp/timer.py
lenhttp/logger.py
lenhttp/lenhttp.py
lenhttp/__init__.py
lenhttp/cutils.cpython-39-x86_64-linux-gnu.so
