Metadata-Version: 2.1
Name: LenHTTP
Version: 2.2.1
Summary: An powerful web framework written from scratch!
Home-page: https://github.com/lenforiee/LenHTTP
Author: Lenforiee
Author-email: lenforiee@misumi.me
License: UNKNOWN
Platform: UNKNOWN
Classifier: Programming Language :: Python :: 3
Classifier: License :: OSI Approved :: MIT License
Classifier: Operating System :: OS Independent
Requires-Python: >=3.8
